jyou/__init__.py
jyou/__main__.py
jyou/config_handler.py
jyou/generator.py
jyou/log.py
jyou/settings.py
jyou/utils.py
JYOU-1.0.dist-info/LICENSE
JYOU-1.0.dist-info/METADATA
JYOU-1.0.dist-info/WHEEL
JYOU-1.0.dist-info/entry_points.txt
JYOU-1.0.dist-info/top_level.txt
JYOU-1.0.dist-info/RECORD
