Metadata-Version: 2.1
Name: JYOU
Version: 1.0
Summary: Simple lockscreen manager for tiling window managers. Generates a lockscreen for multiscreened i3locks
Home-page: http://github.com/slapelachie/jyou
Author: slapelachie
Author-email: slapelachie@gmail.com
License: GPLv3
Platform: UNKNOWN
Classifier: Development Status :: 3 - Alpha
Classifier: Environment :: X11 Applications
Classifier: License :: OSI Approved :: GNU General Public License v3 (GPLv3)
Classifier: Natural Language :: English
Classifier: Operating System :: POSIX :: Linux
Classifier: Programming Language :: Python :: 3.8
Requires-Dist: Pillow
Requires-Dist: tqdm
